xiezuocat/__init__.py
xiezuocat/sm3.py
xiezuocat/sm3_signature_util.py
xiezuocat/xiezuocat.py
xiezuocatpy/__init__.py
xiezuocatpy/sm3.py
xiezuocatpy/sm3_signature_util.py
xiezuocatpy/xiezuocat.py
xiezuocat-2.1.2.dist-info/METADATA
xiezuocat-2.1.2.dist-info/WHEEL
xiezuocat-2.1.2.dist-info/top_level.txt
xiezuocat-2.1.2.dist-info/RECORD
