Metadata-Version: 2.1
Name: xiezuocat
Version: 2.1.2
Summary: 写作猫API及签名算法封装
Home-page: UNKNOWN
Author: metasotadata
Author-email: support@xiezuocat.com
License: apache 3.0
Platform: UNKNOWN
Requires: requests
Requires: json
Requires: time
Requires: base64
